gitlab_runner_tart_driver/__init__.py
gitlab_runner_tart_driver/__main__.py
gitlab_runner_tart_driver/cli.py
gitlab_runner_tart_driver/commands/__init__.py
gitlab_runner_tart_driver/commands/cleanup.py
gitlab_runner_tart_driver/commands/config.py
gitlab_runner_tart_driver/commands/prepare.py
gitlab_runner_tart_driver/commands/run.py
gitlab_runner_tart_driver/modules/__init__.py
gitlab_runner_tart_driver/modules/gitlab_custom_command_config.py
gitlab_runner_tart_driver/modules/gitlab_custom_driver_config.py
gitlab_runner_tart_driver/modules/tart.py
gitlab_runner_tart_driver/modules/utils.py
gitlab_runner_tart_driver/scripts/install-gitlab-runner.sh.j2
gitlab_runner_tart_driver-0.3.12.dist-info/licenses/LICENSE.txt
gitlab_runner_tart_driver-0.3.12.dist-info/METADATA
gitlab_runner_tart_driver-0.3.12.dist-info/WHEEL
gitlab_runner_tart_driver-0.3.12.dist-info/entry_points.txt
gitlab_runner_tart_driver-0.3.12.dist-info/top_level.txt
gitlab_runner_tart_driver-0.3.12.dist-info/RECORD
