Metadata-Version: 2.4
Name: gitlab-runner-tart-driver
Version: 0.3.12
Home-page: https://gitlab.com/schmieder.matthias/gitlab-runner-tart-driver
Author: Matthias Schmieder
Author-email: schmieder.matthias@gmail.com
License: BSD
Classifier: Programming Language :: Python :: 3
Classifier: Programming Language :: Python :: 3.9
Classifier: Intended Audience :: Developers
Classifier: Topic :: Software Development :: Version Control
Requires-Python: >=3.9
License-File: LICENSE.txt
Requires-Dist: click
Requires-Dist: pydantic>=2.0.0
Requires-Dist: pydantic-settings
Requires-Dist: paramiko
Requires-Dist: psutil
Requires-Dist: tabulate
Requires-Dist: jinja2
Dynamic: author
Dynamic: author-email
Dynamic: classifier
Dynamic: description
Dynamic: description-content-type
Dynamic: home-page
Dynamic: license
Dynamic: license-file
Dynamic: requires-dist
Dynamic: requires-python
